hip_pocket
