Metadata-Version: 1.1
Name: HipPocket
Version: 0.1.1-alpha
Summary: A wrapper around Flask to ease the development of larger applications
Home-page: https://github.com/svieira/HipPocket
Author: Sean Vieira
Author-email: vieira.sean+hip_pocket@gmail.com
License: UNKNOWN
Platform: any
Classifier: Development Status :: 2 - Pre-Alpha
Classifier: Environment :: Web Environment
Classifier: Intended Audience :: Developers
Classifier: License :: OSI Approved :: MIT License
Classifier: Operating System :: OS Independent
Classifier: Programming Language :: Python
Classifier: Topic :: Internet :: WWW/HTTP :: Dynamic Content
Classifier: Topic :: Software Development :: Libraries :: Python Modules
